[
  {
    "title": "Өнөр хороололд 2 өрөө",
    "price_text": "1.5 сая ₮",
    "price_value": 1000000,
    "location": "УБ — Баянгол, Баянгол, Хороо 20",
    "district": "УБ — Баянгол",
    "area_sqm": null,
    "rooms": 2,
    "page": 1,
    "scraped_at": "2025-06-05T22:50:22.548350"
  },
  {
    "title": "Худ, 19-р хороолол рaragon төвийн хойно нэхмэл хотхонд 2 өрөө тавилгатай 50 м2",
    "price_text": "1.8 сая ₮",
    "price_value": 1000000,
    "location": "УБ — Хан-Уул, 19-р хороолол",
    "district": "УБ — Хан-Уул",
    "area_sqm": null,
    "rooms": 2,
    "page": 1,
    "scraped_at": "2025-06-05T22:50:22.630290"
  },
  {
    "title": "Кино үйлдвэрт зам дагуу байр 43м2",
    "price_text": "1.2 сая ₮",
    "price_value": 1000000,
    "location": "УБ — Баянзүрх, Баянзүрх, Хороо 13",
    "district": "УБ — Баянзүрх",
    "area_sqm": null,
    "rooms": null,
    "page": 1,
    "scraped_at": "2025-06-05T22:50:22.710018"
  },
  {
    "title": "Бзд, нохойтой хөшөө баруун тийш, том талбайтай 60мкв засвартай 1өрөө",
    "price_text": "1.25 сая ₮",
    "price_value": 1000000,
    "location": "УБ — Баянзүрх, Өгөөмөр захын зүүн",
    "district": "УБ — Баянзүрх",
    "area_sqm": 60.0,
    "rooms": 1,
    "page": 1,
    "scraped_at": "2025-06-05T22:50:22.777998"
  },
  {
    "title": "Худ Алтаргана хотхонд 4 өрөө байр 125мкв",
    "price_text": "3.5 сая ₮",
    "price_value": 3000000,
    "location": "УБ — Хан-Уул, Хан-Уул, Хороо 3",
    "district": "УБ — Хан-Уул",
    "area_sqm": 125.0,
    "rooms": 4,
    "page": 1,
    "scraped_at": "2025-06-05T22:50:22.872189"
  },
  {
    "title": "Төмөр замын 72 байранд 2 өрөө 54м2 байр",
    "price_text": "1.5 сая ₮",
    "price_value": 1000000,
    "location": "УБ — Баянгол, Төмөр зам",
    "district": "УБ — Баянгол",
    "area_sqm": null,
    "rooms": 2,
    "page": 1,
    "scraped_at": "2025-06-05T22:50:22.970823"
  },
  {
    "title": "3-р хороололд 1 өрөө 12 м2 байр",
    "price_text": "790,000 ₮",
    "price_value": 790000,
    "location": "УБ — Баянгол, 3, 4 хороолол",
    "district": "УБ — Баянгол",
    "area_sqm": null,
    "rooms": 1,
    "page": 1,
    "scraped_at": "2025-06-05T22:50:23.044413"
  },
  {
    "title": "2022 оны төмөр зам, вокзал баруун дөрвөн замд хажуу өрөө",
    "price_text": "199,330 ₮ ",
    "price_value": 199330,
    "location": "УБ — Баянгол, Баянгол, Хороо 1",
    "district": "УБ — Баянгол",
    "area_sqm": null,
    "rooms": null,
    "page": 1,
    "scraped_at": "2025-06-05T22:50:23.147425"
  },
  {
    "title": "Зайсан peace village иж бүрэн тавилгатай 3 өрөө 100м зогсоолын хамт",
    "price_text": "3 сая ₮",
    "price_value": 3000000,
    "location": "УБ — Хан-Уул, Хан-Уул, Хороо 11",
    "district": "УБ — Хан-Уул",
    "area_sqm": null,
    "rooms": 3,
    "page": 1,
    "scraped_at": "2025-06-05T22:50:23.411297"
  },
  {
    "title": "Хүннү 2222 хотхонд мастертай 3 өрөө 80мк",
    "price_text": "3.5 сая ₮",
    "price_value": 3000000,
    "location": "УБ — Хан-Уул, Хүннү",
    "district": "УБ — Хан-Уул",
    "area_sqm": 80.0,
    "rooms": 3,
    "page": 1,
    "scraped_at": "2025-06-05T22:50:23.578143"
  },
  {
    "title": "Сүлд хотхонд 6 өрөө 240м2",
    "price_text": "5.5 сая ₮",
    "price_value": 5000000,
    "location": "УБ — Баянзүрх, 15-р хороолол",
    "district": "УБ — Баянзүрх",
    "area_sqm": null,
    "rooms": 6,
    "page": 1,
    "scraped_at": "2025-06-05T22:50:23.763175"
  },
  {
    "title": "Park garden хотхонд 60мкв 3 өрөө орон сууц",
    "price_text": "3.2 сая ₮",
    "price_value": 3000000,
    "location": "УБ — Хан-Уул, Хан-Уул, Хороо 18",
    "district": "УБ — Хан-Уул",
    "area_sqm": 60.0,
    "rooms": 3,
    "page": 1,
    "scraped_at": "2025-06-05T22:50:23.858103"
  },
  {
    "title": "Хотын төвд суис-ийн хажууд 1 өрөө байр",
    "price_text": "1.2 сая ₮",
    "price_value": 1000000,
    "location": "УБ — Чингэлтэй, 5-р сургуулийн ойролцоо",
    "district": "УБ — Чингэлтэй",
    "area_sqm": null,
    "rooms": 1,
    "page": 1,
    "scraped_at": "2025-06-05T22:50:24.010314"
  },
  {
    "title": "Буянт гарден бүрэн тавилгатай 131м2 3 өрөө",
    "price_text": "3.5 сая ₮ ",
    "price_value": 3000000,
    "location": "УБ — Хан-Уул, Хан-Уул, Хороо 23",
    "district": "УБ — Хан-Уул",
    "area_sqm": null,
    "rooms": 3,
    "page": 1,
    "scraped_at": "2025-06-05T22:50:24.258822"
  },
  {
    "title": "Сансарын үйлчилгээний төвийн хажууд 37а байранд 1 өрөө 33мк",
    "price_text": "1.1 сая ₮ 1.2 сая ₮",
    "price_value": 1000000,
    "location": "УБ — Баянзүрх, Сансар",
    "district": "УБ — Баянзүрх",
    "area_sqm": 33.0,
    "rooms": 1,
    "page": 1,
    "scraped_at": "2025-06-05T22:50:24.628627"
  },
  {
    "title": "Худ мишээл экспогийн хойно алтаргана хотхонд 3 өрөө 100мкв",
    "price_text": "3 сая ₮ ",
    "price_value": 3000000,
    "location": "УБ — Хан-Уул, Мишээл",
    "district": "УБ — Хан-Уул",
    "area_sqm": 100.0,
    "rooms": 3,
    "page": 1,
    "scraped_at": "2025-06-05T22:50:24.890615"
  },
  {
    "title": "Бзд ботаник центр хотхонд 51 m2 өрөө байр",
    "price_text": "1.3 сая ₮",
    "price_value": 1000000,
    "location": "УБ — Баянзүрх, Монгол Япон эмнэлэг",
    "district": "УБ — Баянзүрх",
    "area_sqm": null,
    "rooms": 2,
    "page": 1,
    "scraped_at": "2025-06-05T22:50:25.149358"
  },
  {
    "title": "Улсын их дэлгүүрийн ард бүрэн тавилгатай 1 өрөө байр 36мкв",
    "price_text": "1.8 сая ₮",
    "price_value": 1000000,
    "location": "УБ — Чингэлтэй, 40 мянгат",
    "district": "УБ — Чингэлтэй",
    "area_sqm": 36.0,
    "rooms": 1,
    "page": 1,
    "scraped_at": "2025-06-05T22:50:25.360998"
  },
  {
    "title": "Төмөр замын арктай шар байранд гал тогоо тусдаа 80мкв 3 өрөө хагас тавилгатай",
    "price_text": "1.8 сая ₮",
    "price_value": 1000000,
    "location": "УБ — Баянгол, Төмөр зам",
    "district": "УБ — Баянгол",
    "area_sqm": 80.0,
    "rooms": 3,
    "page": 1,
    "scraped_at": "2025-06-05T22:50:25.456102"
  },
  {
    "title": "Их монголд 1 өрөө 30мк",
    "price_text": "1.35 сая ₮ 1.5 сая ₮",
    "price_value": 1000000,
    "location": "УБ — Баянзүрх, Их Монгол хороолол",
    "district": "УБ — Баянзүрх",
    "area_sqm": 30.0,
    "rooms": 1,
    "page": 1,
    "scraped_at": "2025-06-05T22:50:25.546178"
  },
  {
    "title": "Бөхийн өргөөний урд 1 өрөөг 2 өрөө болгож тохижуулсан 36 мкв",
    "price_text": "1.3 сая ₮",
    "price_value": 1000000,
    "location": "УБ — Баянзүрх, 13-р хороолол",
    "district": "УБ — Баянзүрх",
    "area_sqm": 36.0,
    "rooms": 1,
    "page": 1,
    "scraped_at": "2025-06-05T22:50:25.645910"
  },
  {
    "title": "Бзд 16 хороо улаанхуаранд 3 өрөө байр",
    "price_text": "1.65 сая ₮",
    "price_value": 1000000,
    "location": "УБ — Баянзүрх, 16-р хороолол",
    "district": "УБ — Баянзүрх",
    "area_sqm": null,
    "rooms": 3,
    "page": 1,
    "scraped_at": "2025-06-05T22:50:25.745482"
  },
  {
    "title": "Бзд, 26-р хороо, time tower хотхонд 44 мкв 1 өрөө",
    "price_text": "1.6 сая ₮",
    "price_value": 1000000,
    "location": "УБ — Баянзүрх, Баянзүрх, Хороо 26",
    "district": "УБ — Баянзүрх",
    "area_sqm": 44.0,
    "rooms": 1,
    "page": 1,
    "scraped_at": "2025-06-05T22:50:25.857365"
  },
  {
    "title": "Улаанбаатар их дэлгүүр зүүн талд 1 өрөө байр",
    "price_text": "1.5 сая ₮",
    "price_value": 1000000,
    "location": "УБ — Сүхбаатар, Сүхбаатар, Хороо 4",
    "district": "УБ — Сүхбаатар",
    "area_sqm": null,
    "rooms": 1,
    "page": 1,
    "scraped_at": "2025-06-05T22:50:26.067410"
  },
  {
    "title": "Бзд 26 хороо элизабэт хотхонд 74мкв 3 өрөө",
    "price_text": "2.4 сая ₮",
    "price_value": 2000000,
    "location": "УБ — Баянзүрх, Баянзүрх, Хороо 26",
    "district": "УБ — Баянзүрх",
    "area_sqm": 74.0,
    "rooms": 3,
    "page": 1,
    "scraped_at": "2025-06-05T22:50:26.163997"
  },
  {
    "title": "Худ Sky garden-d 5 өрөө байр 203м2",
    "price_text": "15 сая ₮",
    "price_value": 15000000,
    "location": "УБ — Хан-Уул, Marshall town",
    "district": "УБ — Хан-Уул",
    "area_sqm": null,
    "rooms": 5,
    "page": 1,
    "scraped_at": "2025-06-05T22:50:26.244698"
  },
  {
    "title": "Зайсанд 4 өрөө 178 мкв, зогсоолтой",
    "price_text": "4.5 сая ₮",
    "price_value": 4000000,
    "location": "УБ — Хан-Уул, Зайсан",
    "district": "УБ — Хан-Уул",
    "area_sqm": 178.0,
    "rooms": 4,
    "page": 1,
    "scraped_at": "2025-06-05T22:50:26.357110"
  },
  {
    "title": "Алтай хотхонд 2 өрөө 42.10 мкв",
    "price_text": "1.2 сая ₮ 1.4 сая ₮",
    "price_value": 1000000,
    "location": "УБ — Баянгол, Баянгол, Хороо 24",
    "district": "УБ — Баянгол",
    "area_sqm": 42.1,
    "rooms": 2,
    "page": 1,
    "scraped_at": "2025-06-05T22:50:26.446706"
  },
  {
    "title": "Яармаг, нисэх, сонсголонд хажуу өрөө",
    "price_text": "199,330 ₮ ",
    "price_value": 199330,
    "location": "УБ — Хан-Уул, Хан-Уул, Хороо 16",
    "district": "УБ — Хан-Уул",
    "area_sqm": null,
    "rooms": null,
    "page": 1,
    "scraped_at": "2025-06-05T22:50:26.512451"
  },
  {
    "title": "Яармагт бүрэн тавилгатай 2 өрөө байр 90 м2",
    "price_text": "2.5 сая ₮ 2.8 сая ₮",
    "price_value": 2000000,
    "location": "УБ — Хан-Уул, Яармаг",
    "district": "УБ — Хан-Уул",
    "area_sqm": null,
    "rooms": 2,
    "page": 1,
    "scraped_at": "2025-06-05T22:50:26.607514"
  },
  {
    "title": "21r horoolold 1 oroo 31m2",
    "price_text": "1.2 сая ₮",
    "price_value": 1000000,
    "location": "УБ — Сонгинохайрхан, Сонгинохайрхан, Хороо 21",
    "district": "УБ — Сонгинохайрхан",
    "area_sqm": null,
    "rooms": null,
    "page": 1,
    "scraped_at": "2025-06-05T22:50:26.694504"
  },
  {
    "title": "Сэлбийн голын зүүн талд голден вилл хотхонд 3 өрөө байр 81,75м2",
    "price_text": "3 сая ₮",
    "price_value": 3000000,
    "location": "УБ — Баянзүрх, РЦНК",
    "district": "УБ — Баянзүрх",
    "area_sqm": null,
    "rooms": 3,
    "page": 1,
    "scraped_at": "2025-06-05T22:50:26.764873"
  },
  {
    "title": "Хотын төв урланд 3 өрөө байр 70м2",
    "price_text": "2.5 сая ₮",
    "price_value": 2000000,
    "location": "УБ — Сүхбаатар, Сүхбаатар, Хороо 6",
    "district": "УБ — Сүхбаатар",
    "area_sqm": null,
    "rooms": 3,
    "page": 1,
    "scraped_at": "2025-06-05T22:50:26.872067"
  },
  {
    "title": "Seven star-т тавилгатай 2 өрөө 69мк",
    "price_text": "2.8 сая ₮",
    "price_value": 2000000,
    "location": "УБ — Хан-Уул, Зайсан",
    "district": "УБ — Хан-Уул",
    "area_sqm": 69.0,
    "rooms": 2,
    "page": 1,
    "scraped_at": "2025-06-05T22:50:27.058145"
  },
  {
    "title": "Nukht sunset 5 uruu 151мк",
    "price_text": "2.9 сая ₮ 3.1 сая ₮",
    "price_value": 2000000,
    "location": "УБ — Хан-Уул, Нүхтийн ам",
    "district": "УБ — Хан-Уул",
    "area_sqm": 151.0,
    "rooms": null,
    "page": 1,
    "scraped_at": "2025-06-05T22:50:27.211361"
  },
  {
    "title": "Багшийн дээд халдварт шинэ зуун хотхонд хажуу өрөө",
    "price_text": "199,330 ₮ ",
    "price_value": 199330,
    "location": "УБ — Баянзүрх, Баянзүрх, Хороо 18",
    "district": "УБ — Баянзүрх",
    "area_sqm": null,
    "rooms": null,
    "page": 1,
    "scraped_at": "2025-06-05T22:50:27.329741"
  },
  {
    "title": "King tower-т 5 өрөө дуплекс гаднаа терасстай,",
    "price_text": "6 сая ₮",
    "price_value": 6000000,
    "location": "УБ — Хан-Уул, King Tower",
    "district": "УБ — Хан-Уул",
    "area_sqm": null,
    "rooms": 5,
    "page": 1,
    "scraped_at": "2025-06-05T22:50:27.510557"
  },
  {
    "title": "Бзд натурт 2 өрөө 50мк",
    "price_text": "1.3 сая ₮",
    "price_value": 1000000,
    "location": "УБ — Баянзүрх, Баянзүрх, Хороо 25",
    "district": "УБ — Баянзүрх",
    "area_sqm": 50.0,
    "rooms": 2,
    "page": 1,
    "scraped_at": "2025-06-05T22:50:27.623713"
  },
  {
    "title": "Хурд хотхонд 1 өрөө байр",
    "price_text": "1.4 сая ₮",
    "price_value": 1000000,
    "location": "УБ — Хан-Уул, Хан-Уул, Хороо 15",
    "district": "УБ — Хан-Уул",
    "area_sqm": null,
    "rooms": 1,
    "page": 1,
    "scraped_at": "2025-06-05T22:50:27.739790"
  },
  {
    "title": "Кристал таунд 110мкв 4 өрөө байр",
    "price_text": "3.5 сая ₮",
    "price_value": 3000000,
    "location": "УБ — Баянзүрх, Баянзүрх, Хороо 36",
    "district": "УБ — Баянзүрх",
    "area_sqm": 110.0,
    "rooms": 4,
    "page": 1,
    "scraped_at": "2025-06-05T22:50:27.845040"
  },
  {
    "title": "Jukowt 2 oroo 41мк",
    "price_text": "1.3 сая ₮ 1.4 сая ₮",
    "price_value": 1000000,
    "location": "УБ — Баянзүрх, 15-р хороолол",
    "district": "УБ — Баянзүрх",
    "area_sqm": 41.0,
    "rooms": null,
    "page": 1,
    "scraped_at": "2025-06-05T22:50:27.926996"
  },
  {
    "title": "Худ дүүргийн хажууд 2 өрөө 40мк",
    "price_text": "1.6 сая ₮",
    "price_value": 1000000,
    "location": "УБ — Хан-Уул, 19-р хороолол",
    "district": "УБ — Хан-Уул",
    "area_sqm": 40.0,
    "rooms": 2,
    "page": 1,
    "scraped_at": "2025-06-05T22:50:27.988416"
  },
  {
    "title": "11-р хороололд 3 өрөө 70мк",
    "price_text": "1.8 сая ₮",
    "price_value": 1000000,
    "location": "УБ — Сүхбаатар, 11-р хороолол",
    "district": "УБ — Сүхбаатар",
    "area_sqm": 70.0,
    "rooms": 3,
    "page": 1,
    "scraped_at": "2025-06-05T22:50:28.074170"
  },
  {
    "title": "Нэхмэл хотхонд 2 өрөө байр 50м2",
    "price_text": "1.8 сая ₮ 2 сая ₮",
    "price_value": 1000000,
    "location": "УБ — Хан-Уул, Хан-Уул, Хороо 2",
    "district": "УБ — Хан-Уул",
    "area_sqm": null,
    "rooms": 2,
    "page": 1,
    "scraped_at": "2025-06-05T22:50:28.146524"
  },
  {
    "title": "Хүннү 2222 хороололд бүрэн тавилгатай 3 өрөө 79.98мк",
    "price_text": "3.4 сая ₮",
    "price_value": 3000000,
    "location": "УБ — Хан-Уул, Хүннү",
    "district": "УБ — Хан-Уул",
    "area_sqm": 79.98,
    "rooms": 3,
    "page": 1,
    "scraped_at": "2025-06-05T22:50:28.228395"
  },
  {
    "title": "Худ 4 өрөө 112,8м2 байр",
    "price_text": "2.8 сая ₮ ",
    "price_value": 2000000,
    "location": "УБ — Хан-Уул, Хан-Уул, Хороо 22",
    "district": "УБ — Хан-Уул",
    "area_sqm": null,
    "rooms": 4,
    "page": 1,
    "scraped_at": "2025-06-05T22:50:28.307028"
  },
  {
    "title": "Сбд 11-р хороололд 1 өрөө байр 25мкв",
    "price_text": "1.2 сая ₮",
    "price_value": 1000000,
    "location": "УБ — Сүхбаатар, 11-р хороолол",
    "district": "УБ — Сүхбаатар",
    "area_sqm": 25.0,
    "rooms": 1,
    "page": 1,
    "scraped_at": "2025-06-05T22:50:28.395459"
  },
  {
    "title": "Бзд, амгалан амаржихын хажууд 2 өрөө байр 50м2",
    "price_text": "1.5 сая ₮",
    "price_value": 1000000,
    "location": "УБ — Баянзүрх, Амгалан амаржих газар",
    "district": "УБ — Баянзүрх",
    "area_sqm": null,
    "rooms": 2,
    "page": 1,
    "scraped_at": "2025-06-05T22:50:28.464295"
  },
  {
    "title": "Дөлгөөн нуур, хоймор оффисийн баруун талд 1 өрөө тавилгатай байр 25.32m2",
    "price_text": "1.3 сая ₮",
    "price_value": 1000000,
    "location": "УБ — Сүхбаатар, Сүхбаатар, Хороо 9",
    "district": "УБ — Сүхбаатар",
    "area_sqm": null,
    "rooms": 1,
    "page": 1,
    "scraped_at": "2025-06-05T22:50:28.540743"
  },
  {
    "title": "Чд Мөнгөн завьяатай байранд 3 өрөө байр 90мкв",
    "price_text": "3.5 сая ₮",
    "price_value": 3000000,
    "location": "УБ — Чингэлтэй, Чингэлтэй",
    "district": "УБ — Чингэлтэй",
    "area_sqm": 90.0,
    "rooms": 3,
    "page": 1,
    "scraped_at": "2025-06-05T22:50:28.613147"
  },
  {
    "title": "Шангрила river villa хотхонд хажуу өрөө",
    "price_text": "199,330 ₮ ",
    "price_value": 199330,
    "location": "УБ — Хан-Уул, Хан-Уул, Хороо 15",
    "district": "УБ — Хан-Уул",
    "area_sqm": null,
    "rooms": null,
    "page": 1,
    "scraped_at": "2025-06-05T22:50:28.695162"
  },
  {
    "title": "Sky garden 225мк 5 өрөө байр",
    "price_text": "18 сая ₮",
    "price_value": 18000000,
    "location": "УБ — Хан-Уул, Хүннү",
    "district": "УБ — Хан-Уул",
    "area_sqm": 225.0,
    "rooms": 5,
    "page": 1,
    "scraped_at": "2025-06-05T22:50:28.761738"
  },
  {
    "title": "Бзд кино үйлдвэрт ромео жульет хотхонд хажуу өрөө",
    "price_text": "199,330 ₮ ",
    "price_value": 199330,
    "location": "УБ — Баянзүрх, Баянзүрх, Хороо 41",
    "district": "УБ — Баянзүрх",
    "area_sqm": null,
    "rooms": null,
    "page": 1,
    "scraped_at": "2025-06-05T22:50:28.826364"
  },
  {
    "title": "13-р хороололд балконтой 2 өрөө 49мк",
    "price_text": "1.4 сая ₮ 1.8 сая ₮",
    "price_value": 1000000,
    "location": "УБ — Баянзүрх, 13-р хороолол",
    "district": "УБ — Баянзүрх",
    "area_sqm": 49.0,
    "rooms": 2,
    "page": 1,
    "scraped_at": "2025-06-05T22:50:29.079744"
  },
  {
    "title": "Мишээл резидэнс хотхонд 4 өрөө байр 140мкв",
    "price_text": "3.5 сая ₮",
    "price_value": 3000000,
    "location": "УБ — Хан-Уул, Мишээл",
    "district": "УБ — Хан-Уул",
    "area_sqm": 140.0,
    "rooms": 4,
    "page": 1,
    "scraped_at": "2025-06-05T22:50:29.187219"
  },
  {
    "title": "Бгд алтай хотхон 1 өрөө байр 35,73м2",
    "price_text": "1.1 сая ₮",
    "price_value": 1000000,
    "location": "УБ — Баянгол, Алтай хотхон",
    "district": "УБ — Баянгол",
    "area_sqm": null,
    "rooms": 1,
    "page": 1,
    "scraped_at": "2025-06-05T22:50:29.244490"
  },
  {
    "title": "Их монгол хороололд 2 өрөө 42.5 мкв",
    "price_text": "1.8 сая ₮ ",
    "price_value": 1000000,
    "location": "УБ — Баянзүрх, Их Монгол хороолол",
    "district": "УБ — Баянзүрх",
    "area_sqm": 42.5,
    "rooms": 2,
    "page": 1,
    "scraped_at": "2025-06-05T22:50:29.344041"
  },
  {
    "title": "Түмэн наст хотхонд 66мк 2 өрөө байр",
    "price_text": "1.5 сая ₮ ",
    "price_value": 1000000,
    "location": "УБ — Баянзүрх, Баянзүрх, Хороо 42",
    "district": "УБ — Баянзүрх",
    "area_sqm": 66.0,
    "rooms": 2,
    "page": 1,
    "scraped_at": "2025-06-05T22:50:29.479432"
  },
  {
    "title": "Сансарын өндөрт 3 давхарт гал тогоо тусдаа 3 өрөө байр 74м2",
    "price_text": "1.8 сая ₮",
    "price_value": 1000000,
    "location": "УБ — Баянзүрх, Сансар",
    "district": "УБ — Баянзүрх",
    "area_sqm": null,
    "rooms": 3,
    "page": 1,
    "scraped_at": "2025-06-05T22:50:29.595984"
  },
  {
    "title": "Хорооллын эцсийн имартын хажууд хостел",
    "price_text": "600,000 ₮ 780,000 ₮",
    "price_value": 600000,
    "location": "УБ — Баянгол, 3, 4 хороолол",
    "district": "УБ — Баянгол",
    "area_sqm": null,
    "rooms": null,
    "page": 1,
    "scraped_at": "2025-06-05T22:50:29.697041"
  },
  {
    "title": "Сбд 4 хороонд 3 өрөө 58мк",
    "price_text": "2 сая ₮",
    "price_value": 2000000,
    "location": "УБ — Сүхбаатар, Сүхбаатар, Хороо 4",
    "district": "УБ — Сүхбаатар",
    "area_sqm": 58.0,
    "rooms": 3,
    "page": 2,
    "scraped_at": "2025-06-05T22:50:34.535143"
  },
  {
    "title": "Худ 15-р хороо vega city хотхонд 4 өрөө 143.37мк",
    "price_text": "7.7 сая ₮",
    "price_value": 7000000,
    "location": "УБ — Хан-Уул, Хан-Уул, Хороо 15",
    "district": "УБ — Хан-Уул",
    "area_sqm": 143.37,
    "rooms": 4,
    "page": 2,
    "scraped_at": "2025-06-05T22:50:34.713059"
  },
  {
    "title": "Сбд 5 хороололд хажуу өрөө 14мк",
    "price_text": "600,000 ₮",
    "price_value": 600000,
    "location": "УБ — Сүхбаатар, 5-р хороолол",
    "district": "УБ — Сүхбаатар",
    "area_sqm": 14.0,
    "rooms": null,
    "page": 2,
    "scraped_at": "2025-06-05T22:50:34.863243"
  },
  {
    "title": "3,4 хороололд сөөхий-н арын угсармалд 1 өрөө",
    "price_text": "1.5 сая ₮ ",
    "price_value": 1000000,
    "location": "УБ — Баянгол, 3, 4 хороолол",
    "district": "УБ — Баянгол",
    "area_sqm": null,
    "rooms": 1,
    "page": 2,
    "scraped_at": "2025-06-05T22:50:35.009648"
  },
  {
    "title": "Худ 120 мянгат ss garden-д 4 өрөө 141.8m2 байр",
    "price_text": "10.9 сая ₮",
    "price_value": 10000000,
    "location": "УБ — Хан-Уул, Хан-Уул, Хороо 18",
    "district": "УБ — Хан-Уул",
    "area_sqm": null,
    "rooms": 4,
    "page": 2,
    "scraped_at": "2025-06-05T22:50:35.160196"
  },
  {
    "title": "Сансарт 2 өрөө 65м2 байр /хэрэглээ багтсан/",
    "price_text": "1.5 сая ₮",
    "price_value": 1000000,
    "location": "УБ — Баянзүрх, Сансар",
    "district": "УБ — Баянзүрх",
    "area_sqm": null,
    "rooms": 2,
    "page": 2,
    "scraped_at": "2025-06-05T22:50:35.331031"
  },
  {
    "title": "Төмөр замын арктай шар байранд 3 өрөө 80м2 байр тавилгатай",
    "price_text": "2.5 сая ₮",
    "price_value": 2000000,
    "location": "УБ — Баянгол, Төмөр зам",
    "district": "УБ — Баянгол",
    "area_sqm": null,
    "rooms": 3,
    "page": 2,
    "scraped_at": "2025-06-05T22:50:35.611785"
  },
  {
    "title": "Дүнжингарав, цэцэрлэгт хүрээлэнд парк ийст хотхонд хажуу өрөө",
    "price_text": "199,000 ₮ ",
    "price_value": 199000,
    "location": "УБ — Баянзүрх, Үндэсний цэцэрлэгт хүрээлэн",
    "district": "УБ — Баянзүрх",
    "area_sqm": null,
    "rooms": null,
    "page": 2,
    "scraped_at": "2025-06-05T22:50:35.880041"
  },
  {
    "title": "Бөхийн өргөөд 1 өрөө 40м2 байр",
    "price_text": "1.3 сая ₮",
    "price_value": 1000000,
    "location": "УБ — Баянзүрх, Бөхийн Өргөө",
    "district": "УБ — Баянзүрх",
    "area_sqm": null,
    "rooms": 1,
    "page": 2,
    "scraped_at": "2025-06-05T22:50:36.024240"
  },
  {
    "title": "Altai hothond hajuu uruu",
    "price_text": "600,000 ₮",
    "price_value": 600000,
    "location": "УБ — Баянгол, Баянгол, Хороо 24",
    "district": "УБ — Баянгол",
    "area_sqm": null,
    "rooms": null,
    "page": 2,
    "scraped_at": "2025-06-05T22:50:36.145695"
  },
  {
    "title": "Худ 1 өрөө байр 36мкв",
    "price_text": "1.9 сая ₮",
    "price_value": 1000000,
    "location": "УБ — Хан-Уул, Хурд",
    "district": "УБ — Хан-Уул",
    "area_sqm": 36.0,
    "rooms": 1,
    "page": 2,
    "scraped_at": "2025-06-05T22:50:36.287776"
  },
  {
    "title": "Шинэ яармаг цогцолбор хороололд бүрэн тавилгатай 54.40мкв 2 өрөө",
    "price_text": "1.8 сая ₮",
    "price_value": 1000000,
    "location": "УБ — Хан-Уул, Хан-Уул, Хороо 8",
    "district": "УБ — Хан-Уул",
    "area_sqm": 54.4,
    "rooms": 2,
    "page": 2,
    "scraped_at": "2025-06-05T22:50:36.379596"
  },
  {
    "title": "3,4 хороололд хажуу өрөө",
    "price_text": "550,000 ₮",
    "price_value": 550000,
    "location": "УБ — Баянгол, 3, 4 хороолол",
    "district": "УБ — Баянгол",
    "area_sqm": null,
    "rooms": null,
    "page": 2,
    "scraped_at": "2025-06-05T22:50:36.478632"
  },
  {
    "title": "Худ 2 өрөө байр 57м2",
    "price_text": "1.3 сая ₮",
    "price_value": 1000000,
    "location": "УБ — Хан-Уул, 19-р хороолол",
    "district": "УБ — Хан-Уул",
    "area_sqm": null,
    "rooms": 2,
    "page": 2,
    "scraped_at": "2025-06-05T22:50:36.583935"
  },
  {
    "title": "Хажуу өрөө 90м2",
    "price_text": "500,000 ₮",
    "price_value": 500000,
    "location": "УБ — Сүхбаатар, Сүхбаатар, Хороо 9",
    "district": "УБ — Сүхбаатар",
    "area_sqm": null,
    "rooms": null,
    "page": 2,
    "scraped_at": "2025-06-05T22:50:36.658797"
  },
  {
    "title": "Худ 15 хороо рапид харш хотхонд 2 давхрын 2 өрөө 57.7мк",
    "price_text": "1.8 сая ₮",
    "price_value": 1000000,
    "location": "УБ — Хан-Уул, Хурд",
    "district": "УБ — Хан-Уул",
    "area_sqm": 57.7,
    "rooms": 2,
    "page": 2,
    "scraped_at": "2025-06-05T22:50:36.743193"
  },
  {
    "title": "Бзд 26-р нарлаг өргөө хотхонд 4 өрөө байр 85м2 дулаан зогсоолын хамт",
    "price_text": "2.5 сая ₮",
    "price_value": 2000000,
    "location": "УБ — Баянзүрх, Баянзүрх, Хороо 26",
    "district": "УБ — Баянзүрх",
    "area_sqm": null,
    "rooms": 4,
    "page": 2,
    "scraped_at": "2025-06-05T22:50:36.823046"
  },
  {
    "title": "Бгд шинэ хороолол хотхонд 2 өрөө бүрэн тавилгатай орон сууц 44.2мкв",
    "price_text": "1.5 сая ₮",
    "price_value": 1000000,
    "location": "УБ — Баянгол, Баянгол, Хороо 9",
    "district": "УБ — Баянгол",
    "area_sqm": 44.2,
    "rooms": 2,
    "page": 2,
    "scraped_at": "2025-06-05T22:50:36.943842"
  },
  {
    "title": "Хотын төвд багшийн дээдийн урд lux center 200мк 4 өрөө",
    "price_text": "55,000 ₮",
    "price_value": 55000,
    "location": "УБ — Сүхбаатар, Сүхбаатар, Хороо 1",
    "district": "УБ — Сүхбаатар",
    "area_sqm": 200.0,
    "rooms": 4,
    "page": 2,
    "scraped_at": "2025-06-05T22:50:37.011995"
  },
  {
    "title": "1 өрөө байр 41m2",
    "price_text": "1.2 сая ₮",
    "price_value": 1000000,
    "location": "УБ — Баянгол, Баянгол, Хороо 7",
    "district": "УБ — Баянгол",
    "area_sqm": null,
    "rooms": 1,
    "page": 2,
    "scraped_at": "2025-06-05T22:50:37.142743"
  },
  {
    "title": "Sunday хажууд 2 өрөө байр 40м2",
    "price_text": "1.4 сая ₮ 1.5 сая ₮",
    "price_value": 1000000,
    "location": "УБ — Баянзүрх, Сандэй плаза",
    "district": "УБ — Баянзүрх",
    "area_sqm": null,
    "rooms": 2,
    "page": 2,
    "scraped_at": "2025-06-05T22:50:37.247119"
  },
  {
    "title": "Худ, 19-р хороолол 18-р сургууль нутгийн буянгийн байранд 3 өрөө 82мкв орон сууц",
    "price_text": "2.5 сая ₮",
    "price_value": 2000000,
    "location": "УБ — Хан-Уул, 19-р хороолол",
    "district": "УБ — Хан-Уул",
    "area_sqm": 82.0,
    "rooms": 3,
    "page": 2,
    "scraped_at": "2025-06-05T22:50:37.342871"
  },
  {
    "title": "Бзд 13-р хороололд 2 өрөө байр 52мкв",
    "price_text": "1.5 сая ₮ ",
    "price_value": 1000000,
    "location": "УБ — Баянзүрх, 13-р хороолол",
    "district": "УБ — Баянзүрх",
    "area_sqm": 52.0,
    "rooms": 2,
    "page": 2,
    "scraped_at": "2025-06-05T22:50:37.478159"
  },
  {
    "title": "Oros elchingiin urd 3 uruu bair 75mkv",
    "price_text": "2.7 сая ₮ ",
    "price_value": 2000000,
    "location": "УБ — Сүхбаатар, Сүхбаатар, Хороо 2",
    "district": "УБ — Сүхбаатар",
    "area_sqm": null,
    "rooms": null,
    "page": 2,
    "scraped_at": "2025-06-05T22:50:37.634644"
  },
  {
    "title": "Хан-уул дүүргийн зүүн талд 4 өрөө байр",
    "price_text": "2.8 сая ₮ 3 сая ₮",
    "price_value": 2000000,
    "location": "УБ — Хан-Уул, Хан-Уул, Хороо 20",
    "district": "УБ — Хан-Уул",
    "area_sqm": null,
    "rooms": 4,
    "page": 2,
    "scraped_at": "2025-06-05T22:50:37.779408"
  },
  {
    "title": "Хажуу өрөө",
    "price_text": "550,000 ₮",
    "price_value": 550000,
    "location": "УБ — Баянзүрх, Баянзүрх, Хороо 13",
    "district": "УБ — Баянзүрх",
    "area_sqm": null,
    "rooms": null,
    "page": 2,
    "scraped_at": "2025-06-05T22:50:38.022391"
  },
  {
    "title": "хажуу өрөө",
    "price_text": "500,000 ₮",
    "price_value": 500000,
    "location": "УБ — Баянзүрх, 16-р хороолол",
    "district": "УБ — Баянзүрх",
    "area_sqm": null,
    "rooms": null,
    "page": 2,
    "scraped_at": "2025-06-05T22:50:38.324463"
  },
  {
    "title": "1р хороололд 1 өрөө байр",
    "price_text": "1.2 сая ₮",
    "price_value": 1000000,
    "location": "УБ — Сонгинохайрхан, 1-р хороолол",
    "district": "УБ — Сонгинохайрхан",
    "area_sqm": null,
    "rooms": 1,
    "page": 2,
    "scraped_at": "2025-06-05T22:50:38.601033"
  },
  {
    "title": "Бзд 26-р хороо time tower-т 44мкв 1 өрөө",
    "price_text": "1.6 сая ₮",
    "price_value": 1000000,
    "location": "УБ — Баянзүрх, Баянзүрх, Хороо 26",
    "district": "УБ — Баянзүрх",
    "area_sqm": 44.0,
    "rooms": 1,
    "page": 2,
    "scraped_at": "2025-06-05T22:50:38.888609"
  },
  {
    "title": "Бзд хажуу өрөө 24м2",
    "price_text": "350,000 ₮",
    "price_value": 350000,
    "location": "УБ — Баянзүрх, Баянмонгол хороолол",
    "district": "УБ — Баянзүрх",
    "area_sqm": null,
    "rooms": null,
    "page": 2,
    "scraped_at": "2025-06-05T22:50:38.960238"
  },
  {
    "title": "3,4р хорооллын эцэс гссүт-н хажууд 1 өрөө байр 32мкв",
    "price_text": "1.1 сая ₮",
    "price_value": 1000000,
    "location": "УБ — Баянгол, 3, 4 хороолол",
    "district": "УБ — Баянгол",
    "area_sqm": 32.0,
    "rooms": 1,
    "page": 2,
    "scraped_at": "2025-06-05T22:50:39.094287"
  },
  {
    "title": "Бгд Төмөр зам 29мкв 2 өрөө байр",
    "price_text": "1.3 сая ₮ 1.5 сая ₮",
    "price_value": 1000000,
    "location": "УБ — Баянгол, Баянгол, Хороо 1",
    "district": "УБ — Баянгол",
    "area_sqm": 29.0,
    "rooms": 2,
    "page": 2,
    "scraped_at": "2025-06-05T22:50:39.248087"
  },
  {
    "title": "Худ 18-р хороо, гэрлүг виста хотхонд 123мкв бүрэн тавилгатай 123мкв 4 өрөө байр",
    "price_text": "6.5 сая ₮",
    "price_value": 6000000,
    "location": "УБ — Хан-Уул, Хан-Уул, Хороо 18",
    "district": "УБ — Хан-Уул",
    "area_sqm": 123.0,
    "rooms": 4,
    "page": 2,
    "scraped_at": "2025-06-05T22:50:39.378421"
  },
  {
    "title": "Хүннү 2222 хотхонд 3 өрөө 80m2 байр",
    "price_text": "3.5 сая ₮ ",
    "price_value": 3000000,
    "location": "УБ — Хан-Уул, Хүннү",
    "district": "УБ — Хан-Уул",
    "area_sqm": null,
    "rooms": 3,
    "page": 2,
    "scraped_at": "2025-06-05T22:50:39.463944"
  },
  {
    "title": "Чд ард кино театрын урд талд 77м2 3 өрөө байр",
    "price_text": "3 сая ₮",
    "price_value": 3000000,
    "location": "УБ — Чингэлтэй, 40 мянгат",
    "district": "УБ — Чингэлтэй",
    "area_sqm": null,
    "rooms": 3,
    "page": 2,
    "scraped_at": "2025-06-05T22:50:39.529957"
  },
  {
    "title": "Bgd 3, 4 horoоlоl modni 2 dund zam 77 surguuliin urd 1 oroo 35mk bair",
    "price_text": "950,000 ₮",
    "price_value": 950000,
    "location": "УБ — Баянгол, 3, 4 хороолол",
    "district": "УБ — Баянгол",
    "area_sqm": null,
    "rooms": null,
    "page": 2,
    "scraped_at": "2025-06-05T22:50:39.611196"
  },
  {
    "title": "Бзд 33мкв 1 өрөө байр",
    "price_text": "900,000 ₮",
    "price_value": 900000,
    "location": "УБ — Баянзүрх, 16-р хороолол",
    "district": "УБ — Баянзүрх",
    "area_sqm": 33.0,
    "rooms": 1,
    "page": 2,
    "scraped_at": "2025-06-05T22:50:39.707763"
  },
  {
    "title": "Нисэх буянт-ухаа ард байр 3-т хагас тавилгатай 45.34м2 2 өрөө байр",
    "price_text": "1.2 сая ₮",
    "price_value": 1000000,
    "location": "УБ — Хан-Уул, Нисэх",
    "district": "УБ — Хан-Уул",
    "area_sqm": null,
    "rooms": 2,
    "page": 2,
    "scraped_at": "2025-06-05T22:50:39.862291"
  },
  {
    "title": "Kh apartment 2 өрөө 52м2",
    "price_text": "2.2 сая ₮",
    "price_value": 2000000,
    "location": "УБ — Хан-Уул, Хурд",
    "district": "УБ — Хан-Уул",
    "area_sqm": null,
    "rooms": 2,
    "page": 2,
    "scraped_at": "2025-06-05T22:50:39.953326"
  },
  {
    "title": "Зайсанд писс виллаж хотхонд 100 м2 3 өрөө байр дулаан зогсоолын хамт",
    "price_text": "3 сая ₮",
    "price_value": 3000000,
    "location": "УБ — Хан-Уул, Хан-Уул, Хороо 11",
    "district": "УБ — Хан-Уул",
    "area_sqm": null,
    "rooms": 3,
    "page": 2,
    "scraped_at": "2025-06-05T22:50:40.045205"
  },
  {
    "title": "Аманхуур хотхонд 2 өрөө 53.6m2",
    "price_text": "1.5 сая ₮ 1.8 сая ₮",
    "price_value": 1000000,
    "location": "УБ — Баянзүрх, 14-р хороолол",
    "district": "УБ — Баянзүрх",
    "area_sqm": null,
    "rooms": 2,
    "page": 2,
    "scraped_at": "2025-06-05T22:50:40.119575"
  },
  {
    "title": "Bzd 13 horoolold gal togoo tusdaa 1 uruu 18mk",
    "price_text": "1.4 сая ₮",
    "price_value": 1000000,
    "location": "УБ — Баянзүрх, 13-р хороолол",
    "district": "УБ — Баянзүрх",
    "area_sqm": null,
    "rooms": null,
    "page": 2,
    "scraped_at": "2025-06-05T22:50:40.187503"
  },
  {
    "title": "Билэг дэлгүүрийн хойд талд 3 өрөө 42мкв",
    "price_text": "1.7 сая ₮",
    "price_value": 1000000,
    "location": "УБ — Баянгол, 3, 4 хороолол",
    "district": "УБ — Баянгол",
    "area_sqm": 42.0,
    "rooms": 3,
    "page": 2,
    "scraped_at": "2025-06-05T22:50:40.254446"
  },
  {
    "title": "Голден буддагийн урд Гэрэлт хотхонд 108.89 мкв 4 өрөө",
    "price_text": "4.5 сая ₮ ",
    "price_value": 4000000,
    "location": "УБ — Хан-Уул, Хан-Уул, Хороо 11",
    "district": "УБ — Хан-Уул",
    "area_sqm": 108.89,
    "rooms": 4,
    "page": 2,
    "scraped_at": "2025-06-05T22:50:40.329026"
  },
  {
    "title": "Драмын театрын урд элит хотхонд 5 өрөө 192.2м2 байр",
    "price_text": "4 сая ₮ ",
    "price_value": 4000000,
    "location": "УБ — Сүхбаатар, Сүхбаатар, Хороо 1",
    "district": "УБ — Сүхбаатар",
    "area_sqm": null,
    "rooms": 5,
    "page": 2,
    "scraped_at": "2025-06-05T22:50:40.405243"
  },
  {
    "title": "Бзд 1 өрөө байр 35,18м2",
    "price_text": "1.25 сая ₮",
    "price_value": 1000000,
    "location": "УБ — Баянзүрх, Баянзүрх, Хороо 13",
    "district": "УБ — Баянзүрх",
    "area_sqm": null,
    "rooms": 1,
    "page": 2,
    "scraped_at": "2025-06-05T22:50:40.473918"
  },
  {
    "title": "25 эмийн санд 3 өрөө пентхаус 88м2 байр",
    "price_text": "2.3 сая ₮",
    "price_value": 2000000,
    "location": "УБ — Баянгол, 25-р эмийн сан",
    "district": "УБ — Баянгол",
    "area_sqm": null,
    "rooms": 3,
    "page": 2,
    "scraped_at": "2025-06-05T22:50:40.530214"
  },
  {
    "title": "Бгд баруун 4 зам, гандан талдаа 1 өрөө 20мк",
    "price_text": "850,000 ₮ ",
    "price_value": 850000,
    "location": "УБ — Баянгол, Баруун 4 зам",
    "district": "УБ — Баянгол",
    "area_sqm": 20.0,
    "rooms": 1,
    "page": 2,
    "scraped_at": "2025-06-05T22:50:40.595975"
  },
  {
    "title": "Яармагт гумуда 3 өрөө 70м2",
    "price_text": "2.3 сая ₮",
    "price_value": 2000000,
    "location": "УБ — Хан-Уул, Нүхтийн ам",
    "district": "УБ — Хан-Уул",
    "area_sqm": null,
    "rooms": 3,
    "page": 2,
    "scraped_at": "2025-06-05T22:50:40.657823"
  },
  {
    "title": "Peak residenced 115м2 3 өрөө",
    "price_text": "3.8 сая ₮",
    "price_value": 3000000,
    "location": "УБ — Хан-Уул, Хан-Уул, Хороо 11",
    "district": "УБ — Хан-Уул",
    "area_sqm": null,
    "rooms": 3,
    "page": 2,
    "scraped_at": "2025-06-05T22:50:40.727163"
  },
  {
    "title": "Америк илчингийн эсрэг талд 3 өрөө байр 50м2",
    "price_text": "1.6 сая ₮",
    "price_value": 1000000,
    "location": "УБ — Баянзүрх, Баянзүрх, Хороо 1",
    "district": "УБ — Баянзүрх",
    "area_sqm": null,
    "rooms": 3,
    "page": 2,
    "scraped_at": "2025-06-05T22:50:40.794291"
  },
  {
    "title": "Гранд вилла 100м2 дуплекс 3 өрөө",
    "price_text": "4.3 сая ₮",
    "price_value": 4000000,
    "location": "УБ — Баянзүрх, Баянзүрх, Хороо 26",
    "district": "УБ — Баянзүрх",
    "area_sqm": null,
    "rooms": 3,
    "page": 2,
    "scraped_at": "2025-06-05T22:50:40.893870"
  },
  {
    "title": "13 r horoolol 1 uruu 28м2",
    "price_text": "1.1 сая ₮",
    "price_value": 1000000,
    "location": "УБ — Баянзүрх, Баянзүрх, Хороо 43",
    "district": "УБ — Баянзүрх",
    "area_sqm": null,
    "rooms": null,
    "page": 2,
    "scraped_at": "2025-06-05T22:50:40.959146"
  },
  {
    "title": "Дулаан гаражтай, арктай 1 өрөө 43м2",
    "price_text": "1.8 сая ₮",
    "price_value": 1000000,
    "location": "УБ — Хан-Уул, Хан-Уул, Хороо 8",
    "district": "УБ — Хан-Уул",
    "area_sqm": null,
    "rooms": 1,
    "page": 2,
    "scraped_at": "2025-06-05T22:50:41.026280"
  },
  {
    "title": "Сансарт бүрэн тавилгатай 3 өрөө 60m2 байр",
    "price_text": "1.6 сая ₮",
    "price_value": 1000000,
    "location": "УБ — Баянзүрх, Сансар",
    "district": "УБ — Баянзүрх",
    "area_sqm": null,
    "rooms": 3,
    "page": 2,
    "scraped_at": "2025-06-05T22:50:41.093216"
  },
  {
    "title": "Бз дүүрэг 26 хороо элизабет хотхонд 3 өрөө байр",
    "price_text": "2.45 сая ₮",
    "price_value": 2000000,
    "location": "УБ — Баянзүрх, Баянмонгол хороолол",
    "district": "УБ — Баянзүрх",
    "area_sqm": null,
    "rooms": 3,
    "page": 2,
    "scraped_at": "2025-06-05T22:50:41.162076"
  },
  {
    "title": "Шинэ Яармаг хороололд бүрэн тавилгатай 3 өрөө байр 72мкв",
    "price_text": "1.8 сая ₮",
    "price_value": 1000000,
    "location": "УБ — Хан-Уул, Хан-Уул, Хороо 8",
    "district": "УБ — Хан-Уул",
    "area_sqm": 72.0,
    "rooms": 3,
    "page": 2,
    "scraped_at": "2025-06-05T22:50:41.229949"
  },
  {
    "title": "Худ time square хотхонд 140 мкв 4 өрөө+30 мкв террастай байр",
    "price_text": "5.5 сая ₮",
    "price_value": 5000000,
    "location": "УБ — Хан-Уул, River Garden",
    "district": "УБ — Хан-Уул",
    "area_sqm": 140.0,
    "rooms": 4,
    "page": 2,
    "scraped_at": "2025-06-05T22:50:41.333260"
  },
  {
    "title": "Modnii 2t 1 uruu bai 18м2",
    "price_text": "1 сая ₮ 1.2 сая ₮",
    "price_value": 1000000,
    "location": "УБ — Баянгол, Модны 2",
    "district": "УБ — Баянгол",
    "area_sqm": null,
    "rooms": null,
    "page": 2,
    "scraped_at": "2025-06-05T22:50:41.490260"
  },
  {
    "title": "Сансарт 33-р сургуулийн урд талын байранд 83 мкв 3 өрөө тавилгатай, цахилгаан бараатай",
    "price_text": "2.2 сая ₮",
    "price_value": 2000000,
    "location": "УБ — Баянзүрх, Сансар",
    "district": "УБ — Баянзүрх",
    "area_sqm": 83.0,
    "rooms": 3,
    "page": 2,
    "scraped_at": "2025-06-05T22:50:41.594865"
  },
  {
    "title": "River plaza 230sqm 5 room 3 bedroom, workplace with cozy living room + 1 garage",
    "price_text": "15 сая ₮ ",
    "price_value": 15000000,
    "location": "УБ — Хан-Уул, River Garden",
    "district": "УБ — Хан-Уул",
    "area_sqm": null,
    "rooms": null,
    "page": 3,
    "scraped_at": "2025-06-05T22:50:46.893152"
  },
  {
    "title": "Баянмонгол хорооллын хойно нарны зам дагуу эмэгтэй хостел",
    "price_text": "320,000 ₮",
    "price_value": 320000,
    "location": "УБ — Баянзүрх, Баянмонгол хороолол",
    "district": "УБ — Баянзүрх",
    "area_sqm": null,
    "rooms": null,
    "page": 3,
    "scraped_at": "2025-06-05T22:50:47.178476"
  },
  {
    "title": "Буянт-ухаа1 702-р байр 1 өрөө 39,7м2 байр",
    "price_text": "1.1 сая ₮",
    "price_value": 1000000,
    "location": "УБ — Хан-Уул, Хан-Уул, Хороо 25",
    "district": "УБ — Хан-Уул",
    "area_sqm": null,
    "rooms": 1,
    "page": 3,
    "scraped_at": "2025-06-05T22:50:47.389859"
  },
  {
    "title": "Sky garden residence-д 4 өрөө орон сууц 146м2",
    "price_text": "10 сая ₮",
    "price_value": 10000000,
    "location": "УБ — Хан-Уул, River Garden",
    "district": "УБ — Хан-Уул",
    "area_sqm": null,
    "rooms": 4,
    "page": 3,
    "scraped_at": "2025-06-05T22:50:47.556345"
  },
  {
    "title": "БЗД, 16-р хороололд 28 мкв 1 өрөө",
    "price_text": "900,000 ₮",
    "price_value": 900000,
    "location": "УБ — Баянзүрх, 16-р хороолол",
    "district": "УБ — Баянзүрх",
    "area_sqm": 28.0,
    "rooms": 1,
    "page": 3,
    "scraped_at": "2025-06-05T22:50:47.704936"
  },
  {
    "title": "Сансарт клонкын эсрэг талын амины орон сууцанд хажуу том өрөө 28мк",
    "price_text": "600,000 ₮",
    "price_value": 600000,
    "location": "УБ — Баянзүрх, Сансар",
    "district": "УБ — Баянзүрх",
    "area_sqm": 28.0,
    "rooms": null,
    "page": 3,
    "scraped_at": "2025-06-05T22:50:47.912356"
  },
  {
    "title": "Будда виста 122 мкв 4 өрөө байр",
    "price_text": "6.5 сая ₮ ",
    "price_value": 6000000,
    "location": "УБ — Хан-Уул, Bella Vista",
    "district": "УБ — Хан-Уул",
    "area_sqm": 122.0,
    "rooms": 4,
    "page": 3,
    "scraped_at": "2025-06-05T22:50:48.038993"
  },
  {
    "title": "Худ роял гарден хотхонд 210м2, тавилгатай 6 өрөө",
    "price_text": "8.5 сая ₮",
    "price_value": 8000000,
    "location": "УБ — Хан-Уул, Хан-Уул, Хороо 18",
    "district": "УБ — Хан-Уул",
    "area_sqm": null,
    "rooms": 6,
    "page": 3,
    "scraped_at": "2025-06-05T22:50:48.158763"
  },
  {
    "title": "Худ gerlug vista хотхонд 4 өрөө 123мк",
    "price_text": "7 сая ₮",
    "price_value": 7000000,
    "location": "УБ — Хан-Уул, Хан-Уул, Хороо 18",
    "district": "УБ — Хан-Уул",
    "area_sqm": 123.0,
    "rooms": 4,
    "page": 3,
    "scraped_at": "2025-06-05T22:50:48.312340"
  },
  {
    "title": "Бзд сансарын баянцээлд гал тогоо тусдаа 2 өрөө байр 60мкв",
    "price_text": "1.5 сая ₮",
    "price_value": 1000000,
    "location": "УБ — Баянзүрх, Сансар",
    "district": "УБ — Баянзүрх",
    "area_sqm": 60.0,
    "rooms": 2,
    "page": 3,
    "scraped_at": "2025-06-05T22:50:48.448118"
  },
  {
    "title": "Alpha zonе-д тавилгатай 3 өрөө 103.5мк байр",
    "price_text": "4.5 сая ₮",
    "price_value": 4000000,
    "location": "УБ — Хан-Уул, Хан-Уул, Хороо 15",
    "district": "УБ — Хан-Уул",
    "area_sqm": 103.5,
    "rooms": 3,
    "page": 3,
    "scraped_at": "2025-06-05T22:50:48.710163"
  },
  {
    "title": "Han-uul duureg 3-r horoo telmuund hothon 2 uruu bair",
    "price_text": "1.25 сая ₮",
    "price_value": 1000000,
    "location": "УБ — Хан-Уул, Хан-Уул, Хороо 3",
    "district": "УБ — Хан-Уул",
    "area_sqm": null,
    "rooms": null,
    "page": 3,
    "scraped_at": "2025-06-05T22:50:48.803643"
  },
  {
    "title": "Жуковт 2 өрөө 44мкв байр",
    "price_text": "1.6 сая ₮ 1.8 сая ₮",
    "price_value": 1000000,
    "location": "УБ — Баянзүрх, Баянзүрх, Хороо 5",
    "district": "УБ — Баянзүрх",
    "area_sqm": 44.0,
    "rooms": 2,
    "page": 3,
    "scraped_at": "2025-06-05T22:50:48.922977"
  },
  {
    "title": "Rapid hothond 2 uruu 69м2 bair",
    "price_text": "2.8 сая ₮",
    "price_value": 2000000,
    "location": "УБ — Хан-Уул, Хурд",
    "district": "УБ — Хан-Уул",
    "area_sqm": null,
    "rooms": null,
    "page": 3,
    "scraped_at": "2025-06-05T22:50:48.993176"
  },
  {
    "title": "Олимп хотхонд 3 өрөө байр",
    "price_text": "2.2 сая ₮",
    "price_value": 2000000,
    "location": "УБ — Баянзүрх, Olympic village",
    "district": "УБ — Баянзүрх",
    "area_sqm": null,
    "rooms": 3,
    "page": 3,
    "scraped_at": "2025-06-05T22:50:49.075590"
  },
  {
    "title": "Japantown c3 4 өрөө 118.9м2 байр",
    "price_text": "5 сая ₮",
    "price_value": 5000000,
    "location": "УБ — Хан-Уул, Japan town",
    "district": "УБ — Хан-Уул",
    "area_sqm": null,
    "rooms": 4,
    "page": 3,
    "scraped_at": "2025-06-05T22:50:49.152956"
  },
  {
    "title": "Бзд 14-р хороонд бүрэн тавилгатай 2 өрөө орон сууц 40m2",
    "price_text": "1.5 сая ₮",
    "price_value": 1000000,
    "location": "УБ — Баянзүрх, 14-р хороолол",
    "district": "УБ — Баянзүрх",
    "area_sqm": null,
    "rooms": 2,
    "page": 3,
    "scraped_at": "2025-06-05T22:50:49.222620"
  },
  {
    "title": "Сансар гарденд 96.86 мкв 4 өрөө байр хөлслүүлнэ. бүрэн тавилгатай+граштай",
    "price_text": "4 сая ₮",
    "price_value": 4000000,
    "location": "УБ — Баянзүрх, Чингис зочид буудал",
    "district": "УБ — Баянзүрх",
    "area_sqm": 96.86,
    "rooms": 4,
    "page": 3,
    "scraped_at": "2025-06-05T22:50:49.296962"
  },
  {
    "title": "5-р сургуулийн баруун талд 55м2 3 өрөө",
    "price_text": "2.7 сая ₮",
    "price_value": 2000000,
    "location": "УБ — Чингэлтэй, Чингэлтэй, Хороо 4",
    "district": "УБ — Чингэлтэй",
    "area_sqm": null,
    "rooms": 3,
    "page": 3,
    "scraped_at": "2025-06-05T22:50:49.372497"
  },
  {
    "title": "Бзд ктмс-н зүүн хойно сүлд хотхонд 6 өрөө дуплекс орон сууц 240м2",
    "price_text": "5.5 сая ₮",
    "price_value": 5000000,
    "location": "УБ — Баянзүрх, Баянзүрх, Хороо 2",
    "district": "УБ — Баянзүрх",
    "area_sqm": null,
    "rooms": 6,
    "page": 3,
    "scraped_at": "2025-06-05T22:50:49.438626"
  },
  {
    "title": "5-р сургуулийн баруун урд талд 32 м2 2 өрөө",
    "price_text": "2.1 сая ₮",
    "price_value": 2000000,
    "location": "УБ — Чингэлтэй, Чингэлтэй, Хороо 3",
    "district": "УБ — Чингэлтэй",
    "area_sqm": null,
    "rooms": 2,
    "page": 3,
    "scraped_at": "2025-06-05T22:50:49.508043"
  },
  {
    "title": "19-р хороололд 4 өрөө 90мк",
    "price_text": "3.2 сая ₮",
    "price_value": 3000000,
    "location": "УБ — Хан-Уул, 19-р хороолол",
    "district": "УБ — Хан-Уул",
    "area_sqm": 90.0,
    "rooms": 4,
    "page": 3,
    "scraped_at": "2025-06-05T22:50:49.576081"
  },
  {
    "title": "Бзд 26-р хороо чухаг 2 хотхонд бүрэн тавилгатай 3 өрөө 76.17мк",
    "price_text": "2.5 сая ₮",
    "price_value": 2000000,
    "location": "УБ — Баянзүрх, Баянзүрх, Хороо 26",
    "district": "УБ — Баянзүрх",
    "area_sqm": 76.17,
    "rooms": 3,
    "page": 3,
    "scraped_at": "2025-06-05T22:50:49.643991"
  },
  {
    "title": "Циркийн хажууд time classic -т 117 мкв 4 өрөө",
    "price_text": "6.5 сая ₮",
    "price_value": 6000000,
    "location": "УБ — Сүхбаатар, Наран плаза",
    "district": "УБ — Сүхбаатар",
    "area_sqm": 117.0,
    "rooms": 4,
    "page": 3,
    "scraped_at": "2025-06-05T22:50:49.722098"
  },
  {
    "title": "Polaris 2 appartment- nisehed 3 uruu 72m2 bair",
    "price_text": "1.4 сая ₮ ",
    "price_value": 1000000,
    "location": "УБ — Хан-Уул, Хан-Уул, Хороо 21",
    "district": "УБ — Хан-Уул",
    "area_sqm": null,
    "rooms": null,
    "page": 3,
    "scraped_at": "2025-06-05T22:50:49.804799"
  },
  {
    "title": "Сансарт 97-р сургуулийн урд байранд хажуу өрөө",
    "price_text": "550,000 ₮",
    "price_value": 550000,
    "location": "УБ — Баянзүрх, 15-р хороолол",
    "district": "УБ — Баянзүрх",
    "area_sqm": null,
    "rooms": null,
    "page": 3,
    "scraped_at": "2025-06-05T22:50:49.921808"
  },
  {
    "title": "Xotiin a busd amerik elchingiin urd selbe goliin zuun tald buren tavilgatai 1 uruu",
    "price_text": "1.3 сая ₮",
    "price_value": 1000000,
    "location": "УБ — Баянзүрх, Баянзүрх, Хороо 1",
    "district": "УБ — Баянзүрх",
    "area_sqm": null,
    "rooms": null,
    "page": 3,
    "scraped_at": "2025-06-05T22:50:50.009241"
  },
  {
    "title": "Сансарт 3 өрөө 40мк",
    "price_text": "1.7 сая ₮",
    "price_value": 1000000,
    "location": "УБ — Баянзүрх, Сансар",
    "district": "УБ — Баянзүрх",
    "area_sqm": 40.0,
    "rooms": 3,
    "page": 3,
    "scraped_at": "2025-06-05T22:50:50.128338"
  },
  {
    "title": "Хурд рапид хороололд 3 өрөө 76мк",
    "price_text": "2.6 сая ₮",
    "price_value": 2000000,
    "location": "УБ — Хан-Уул, Хурд",
    "district": "УБ — Хан-Уул",
    "area_sqm": 76.0,
    "rooms": 3,
    "page": 3,
    "scraped_at": "2025-06-05T22:50:50.211872"
  },
  {
    "title": "Будда вистад 4 өрөө 122м.кв байр",
    "price_text": "6 сая ₮ ",
    "price_value": 6000000,
    "location": "УБ — Хан-Уул, Зайсан",
    "district": "УБ — Хан-Уул",
    "area_sqm": null,
    "rooms": 4,
    "page": 3,
    "scraped_at": "2025-06-05T22:50:50.293452"
  },
  {
    "title": "Нисэх шүрт хотхонд 2 өрөө байр 42.48мкв",
    "price_text": "1.2 сая ₮",
    "price_value": 1000000,
    "location": "УБ — Хан-Уул, Нисэх",
    "district": "УБ — Хан-Уул",
    "area_sqm": 42.48,
    "rooms": 2,
    "page": 3,
    "scraped_at": "2025-06-05T22:50:50.417956"
  },
  {
    "title": "Зайсан рома таун хотхонд 90м2 3 өрөө бүрэн тавилгатай дулаан гараштай байр",
    "price_text": "3 сая ₮ 3.2 сая ₮ ",
    "price_value": 3000000,
    "location": "УБ — Хан-Уул, Зайсан",
    "district": "УБ — Хан-Уул",
    "area_sqm": null,
    "rooms": 3,
    "page": 3,
    "scraped_at": "2025-06-05T22:50:50.660172"
  },
  {
    "title": "Бгд төмөр замд 1 өрөө 32мк",
    "price_text": "1.1 сая ₮ ",
    "price_value": 1000000,
    "location": "УБ — Баянгол, Төмөр зам",
    "district": "УБ — Баянгол",
    "area_sqm": 32.0,
    "rooms": 1,
    "page": 3,
    "scraped_at": "2025-06-05T22:50:51.045712"
  },
  {
    "title": "13-р хороолол бөхийн өргөөний урд 1 өрөө 42мк",
    "price_text": "1.6 сая ₮",
    "price_value": 1000000,
    "location": "УБ — Баянзүрх, 13-р хороолол",
    "district": "УБ — Баянзүрх",
    "area_sqm": 42.0,
    "rooms": 1,
    "page": 3,
    "scraped_at": "2025-06-05T22:50:51.258668"
  },
  {
    "title": "Худ Цэнгэлдэхийн урд роял гарден хотхонд хагас тавилгатай 154мкв 4 өрөө",
    "price_text": "5.5 сая ₮",
    "price_value": 5000000,
    "location": "УБ — Хан-Уул, Japan town",
    "district": "УБ — Хан-Уул",
    "area_sqm": 154.0,
    "rooms": 4,
    "page": 3,
    "scraped_at": "2025-06-05T22:50:51.423710"
  },
  {
    "title": "Схд хархорин захын дэргэд төв зам дагуу буудлын дэргэд хажуу өрөө",
    "price_text": "199,330 ₮ ",
    "price_value": 199330,
    "location": "УБ — Сонгинохайрхан, 1-р хороолол",
    "district": "УБ — Сонгинохайрхан",
    "area_sqm": null,
    "rooms": null,
    "page": 3,
    "scraped_at": "2025-06-05T22:50:51.691643"
  },
  {
    "title": "Зүүн 4 замын байранд 70мкв хажуу өрөө",
    "price_text": "199,330 ₮ ",
    "price_value": 199330,
    "location": "УБ — Баянзүрх, Зүүн 4 зам",
    "district": "УБ — Баянзүрх",
    "area_sqm": 70.0,
    "rooms": null,
    "page": 3,
    "scraped_at": "2025-06-05T22:50:51.980312"
  },
  {
    "title": "Яармаг green art 2 өрөө 44м2 байр",
    "price_text": "1.5 сая ₮",
    "price_value": 1000000,
    "location": "УБ — Хан-Уул, Яармаг",
    "district": "УБ — Хан-Уул",
    "area_sqm": null,
    "rooms": 2,
    "page": 3,
    "scraped_at": "2025-06-05T22:50:52.245333"
  },
  {
    "title": "Цагаан хуаран хотхон 2 өрөө 39м2 байр",
    "price_text": "1.25 сая ₮ 1.35 сая ₮",
    "price_value": 1000000,
    "location": "УБ — Баянзүрх, 14-р хороолол",
    "district": "УБ — Баянзүрх",
    "area_sqm": null,
    "rooms": 2,
    "page": 3,
    "scraped_at": "2025-06-05T22:50:52.403365"
  },
  {
    "title": "Зайсанд тавилгатай, дулаан зогсоолтой 3 өрөө байр 91м2",
    "price_text": "2.5 сая ₮",
    "price_value": 2000000,
    "location": "УБ — Хан-Уул, Зайсан",
    "district": "УБ — Хан-Уул",
    "area_sqm": null,
    "rooms": 3,
    "page": 3,
    "scraped_at": "2025-06-05T22:50:52.494693"
  },
  {
    "title": "Худ хансвилл хотхонд 86 мкв 3 өрөө",
    "price_text": "2.4 сая ₮",
    "price_value": 2000000,
    "location": "УБ — Хан-Уул, Хан-Уул, Хороо 15",
    "district": "УБ — Хан-Уул",
    "area_sqm": 86.0,
    "rooms": 3,
    "page": 3,
    "scraped_at": "2025-06-05T22:50:52.631254"
  },
  {
    "title": "Замын цагдаагын зүүн талд бүрэн тавилагатай 1 өрөө",
    "price_text": "1.2 сая ₮",
    "price_value": 1000000,
    "location": "УБ — Сүхбаатар, Сүхбаатар, Хороо 1",
    "district": "УБ — Сүхбаатар",
    "area_sqm": null,
    "rooms": 1,
    "page": 3,
    "scraped_at": "2025-06-05T22:50:52.754511"
  },
  {
    "title": "Зүүн 4 замын американ дэнж хотхоны урд гал тогоо тусдаа 2 өрөө байр",
    "price_text": "1.3 сая ₮",
    "price_value": 1000000,
    "location": "УБ — Баянзүрх, Зүүн 4 зам",
    "district": "УБ — Баянзүрх",
    "area_sqm": null,
    "rooms": 2,
    "page": 3,
    "scraped_at": "2025-06-05T22:50:52.875333"
  },
  {
    "title": "13-р хороололд гал тогоо тусдаа, бүрэн тавилгатай 1 өрөө байр",
    "price_text": "1.8 сая ₮",
    "price_value": 1000000,
    "location": "УБ — Баянзүрх, 13-р хороолол",
    "district": "УБ — Баянзүрх",
    "area_sqm": null,
    "rooms": 1,
    "page": 3,
    "scraped_at": "2025-06-05T22:50:53.004216"
  },
  {
    "title": "Бгд 10-р хороолол 2 өрөө тавилгатай байр 32м2",
    "price_text": "1.5 сая ₮ 1.7 сая ₮",
    "price_value": 1000000,
    "location": "УБ — Баянгол, 10-р хороолол",
    "district": "УБ — Баянгол",
    "area_sqm": null,
    "rooms": 2,
    "page": 3,
    "scraped_at": "2025-06-05T22:50:53.089483"
  },
  {
    "title": "Бгд хажуу өрөө",
    "price_text": "550,000 ₮",
    "price_value": 550000,
    "location": "УБ — Баянгол, Баянгол, Хороо 1",
    "district": "УБ — Баянгол",
    "area_sqm": null,
    "rooms": null,
    "page": 3,
    "scraped_at": "2025-06-05T22:50:53.163170"
  },
  {
    "title": "Crystal od кристал од тансаг зэрэглэлийн орон сууцанд хажуу өрөө",
    "price_text": "199,330 ₮ ",
    "price_value": 199330,
    "location": "УБ — Баянгол, Баянгол, Хороо 2",
    "district": "УБ — Баянгол",
    "area_sqm": null,
    "rooms": null,
    "page": 3,
    "scraped_at": "2025-06-05T22:50:53.242123"
  },
  {
    "title": "Зайсан ub town хотхонд 2 өрөө байр 58м2",
    "price_text": "2 сая ₮",
    "price_value": 2000000,
    "location": "УБ — Хан-Уул, 19-р хороолол",
    "district": "УБ — Хан-Уул",
    "area_sqm": null,
    "rooms": 2,
    "page": 3,
    "scraped_at": "2025-06-05T22:50:53.328190"
  },
  {
    "title": "Бгд хорооллын эцэст 3 өрөө 80мкв",
    "price_text": "1.5 сая ₮ 1.6 сая ₮",
    "price_value": 1000000,
    "location": "УБ — Баянгол, 4-р хороолол",
    "district": "УБ — Баянгол",
    "area_sqm": 80.0,
    "rooms": 3,
    "page": 3,
    "scraped_at": "2025-06-05T22:50:53.522964"
  },
  {
    "title": "мишээл 1 өрөө бүрэн тавилгатай байр",
    "price_text": "1.3 сая ₮",
    "price_value": 1000000,
    "location": "УБ — Хан-Уул, Мишээл",
    "district": "УБ — Хан-Уул",
    "area_sqm": null,
    "rooms": 1,
    "page": 3,
    "scraped_at": "2025-06-05T22:50:53.663245"
  },
  {
    "title": "Худ хурдын рапид 3 өрөө 67м2",
    "price_text": "2 сая ₮ 2.5 сая ₮",
    "price_value": 2000000,
    "location": "УБ — Хан-Уул, Хурд",
    "district": "УБ — Хан-Уул",
    "area_sqm": null,
    "rooms": 3,
    "page": 3,
    "scraped_at": "2025-06-05T22:50:53.887366"
  },
  {
    "title": "Зайсан грийн вилла 7 өрөө 400м2",
    "price_text": "8 сая ₮ ",
    "price_value": 8000000,
    "location": "УБ — Хан-Уул, Зайсан",
    "district": "УБ — Хан-Уул",
    "area_sqm": null,
    "rooms": 7,
    "page": 3,
    "scraped_at": "2025-06-05T22:50:54.088949"
  },
  {
    "title": "Худ 11-р хороо khanhills хотхонд 4 өрөө орон сууц 140.7мкв",
    "price_text": "5 сая ₮",
    "price_value": 5000000,
    "location": "УБ — Хан-Уул, Хан-Уул, Хороо 11",
    "district": "УБ — Хан-Уул",
    "area_sqm": 140.7,
    "rooms": 4,
    "page": 3,
    "scraped_at": "2025-06-05T22:50:54.276829"
  },
  {
    "title": "Сансарт гал тогоо тусдаа 1 өрөө байр 40мкв",
    "price_text": "1.2 сая ₮",
    "price_value": 1000000,
    "location": "УБ — Баянзүрх, Сансар",
    "district": "УБ — Баянзүрх",
    "area_sqm": 40.0,
    "rooms": 1,
    "page": 3,
    "scraped_at": "2025-06-05T22:50:54.395640"
  },
  {
    "title": "Мандала хотхонд бүрэн тавилгатай 98м2 тай 4 өрөө байр",
    "price_text": "4 сая ₮",
    "price_value": 4000000,
    "location": "УБ — Баянзүрх, Баянзүрх, Хороо 26",
    "district": "УБ — Баянзүрх",
    "area_sqm": null,
    "rooms": 4,
    "page": 3,
    "scraped_at": "2025-06-05T22:50:54.593716"
  },
  {
    "title": "1-р хороолол цамбагаравт, төв зам дагуу буудлын дэргэд, 138 м.кв 4 өрөө",
    "price_text": "2 сая ₮ 2.5 сая ₮",
    "price_value": 2000000,
    "location": "УБ — Баянгол, Баянгол, Хороо 29",
    "district": "УБ — Баянгол",
    "area_sqm": null,
    "rooms": 4,
    "page": 3,
    "scraped_at": "2025-06-05T22:50:54.761104"
  },
  {
    "title": "Натурт маш цэвэрхэн хажуу өрөө гадаадын иргэнд",
    "price_text": "750,000 ₮",
    "price_value": 750000,
    "location": "УБ — Баянзүрх, 13-р хороолол",
    "district": "УБ — Баянзүрх",
    "area_sqm": null,
    "rooms": null,
    "page": 3,
    "scraped_at": "2025-06-05T22:50:54.958651"
  },
  {
    "title": "Найрамдалд 2 өрөө 70мк орон сууц",
    "price_text": "2.5 сая ₮ ",
    "price_value": 2000000,
    "location": "УБ — Сонгинохайрхан, Найрамдал",
    "district": "УБ — Сонгинохайрхан",
    "area_sqm": 70.0,
    "rooms": 2,
    "page": 3,
    "scraped_at": "2025-06-05T22:50:55.163313"
  },
  {
    "title": "Яармаг 1-р буудал хажуу өрөө",
    "price_text": "499,900 ₮",
    "price_value": 499900,
    "location": "УБ — Хан-Уул, Яармаг",
    "district": "УБ — Хан-Уул",
    "area_sqm": null,
    "rooms": null,
    "page": 3,
    "scraped_at": "2025-06-05T22:50:55.399865"
  },
  {
    "title": "Нарантуул захын ард шинэ үе хотхонд 33 мкв 1 өрөө байр",
    "price_text": "950,000 ₮ 1.1 сая ₮",
    "price_value": 950000000000,
    "location": "УБ — Баянзүрх, Өгөөмөр захын зүүн",
    "district": "УБ — Баянзүрх",
    "area_sqm": 33.0,
    "rooms": 1,
    "page": 3,
    "scraped_at": "2025-06-05T22:50:55.654813"
  }
]